django_dynamicadmin/__init__.py
django_dynamicadmin/settings.py
django_dynamicadmin/settings_test.py
django_dynamicadmin/urls.py
django_dynamicadmin/wsgi.py
dynamicadmin/__init__.py
dynamicadmin/admin.py
dynamicadmin/apps.py
dynamicadmin/models.py
dynamicadmin/views.py
dynamicadmin/bundle/__init__.py
dynamicadmin/bundle/admin.py
dynamicadmin/bundle/models.py
dynamicadmin/entity/__init__.py
dynamicadmin/entity/models.py
dynamicadmin/migrations/0001_initial.py
dynamicadmin/migrations/__init__.py
dynamicadmin/taxonomy/__init__.py
dynamicadmin/taxonomy/models.py
dynamicadmin/tests/__init__.py
dynamicadmin/tests/test_models.py
dynamicadmin/tests/tests_bundle_app/__init__.py
dynamicadmin/tests/tests_bundle_app/models.py
dynamicadmin/tests/tests_bundle_app/migrations/0001_initial.py
dynamicadmin/tests/tests_bundle_app/migrations/__init__.py
dynamicadmin/tests/tests_dynamic_app/__init__.py
dynamicadmin/tests/tests_dynamic_app/migrations/0001_initial.py
dynamicadmin/tests/tests_dynamic_app/migrations/__init__.py
django_dynamic_admin-0.3.0.dist-info/LICENSE
django_dynamic_admin-0.3.0.dist-info/METADATA
django_dynamic_admin-0.3.0.dist-info/WHEEL
django_dynamic_admin-0.3.0.dist-info/top_level.txt
django_dynamic_admin-0.3.0.dist-info/RECORD
