Metadata-Version: 2.1
Name: django-dynamic-admin
Version: 0.3.0
Summary: Create dynamic models from Django administration
Home-page: https://github.com/seht/django-dynamic-admin
Author: Seht
Author-email: seht@hyx.net
License: BSD License
Platform: UNKNOWN
Classifier: License :: OSI Approved :: BSD License
Classifier: Environment :: Web Environment
Classifier: Operating System :: OS Independent
Classifier: Intended Audience :: Developers
Classifier: Framework :: Django
Classifier: Framework :: Django :: 2.0
Classifier: Framework :: Django :: 2.1
Classifier: Framework :: Django :: 2.2
Classifier: Programming Language :: Python :: 3
Classifier: Programming Language :: Python :: 3.6
Classifier: Programming Language :: Python :: 3.7
Classifier: Programming Language :: Python :: 3.8
Classifier: Topic :: Internet :: WWW/HTTP
Classifier: Topic :: Internet :: WWW/HTTP :: Dynamic Content
Requires-Python: >=3.5
Requires-Dist: django (>=2.0)
Requires-Dist: django-polymorphic (>=2.0)
